lc_power_match_baluns/__init__.py
lc_power_match_baluns/oneport.py
lc_power_match_baluns/topology.py
lc_power_match_baluns-2.0.1.dist-info/LICENSE
lc_power_match_baluns-2.0.1.dist-info/METADATA
lc_power_match_baluns-2.0.1.dist-info/WHEEL
lc_power_match_baluns-2.0.1.dist-info/top_level.txt
lc_power_match_baluns-2.0.1.dist-info/RECORD
