Metadata-Version: 2.1
Name: lc-power-match-baluns
Version: 2.0.1
Summary: Models power matching LC-baluns
Author-email: Rasmus Jepsen <rasale@dtu.dk>
License: LGPL-2.1-or-later
Project-URL: Homepage, https://github.com/dtudk/lc-power-match-baluns
Project-URL: Bug Tracker, https://github.com/dtudk/lc-power-match-baluns/issues
Classifier: Programming Language :: Python :: 3
Classifier: Operating System :: OS Independent
Requires-Python: >=3.10
License-File: LICENSE
Requires-Dist: lcapy>=1.15
Requires-Dist: numpy>=1.24.3
Requires-Dist: sympy>=1.12
Requires-Dist: scikit_rf>=0.31.0
Requires-Dist: multimethod>=1.11.2
